[{"senderKeyId":1350461005,"senderChainKey":{"iteration":247,"seed":"d/7mDLrc27boSlIg2RdPXLl/DI6sq20dMfrqD3F1qKM="},"senderSigningKey":{"public":"BeKtHMvUMI4OJXafTyuUg8CqRv23yYJYnekTlfmRXVdg","private":"sPrJ9GTMvDtG+4x+cIRegbmZKe2r7IbmQ60G2Dvmj20="},"senderMessageKeys":[{},{},{},{},{},{},{},{},{},{},{},{},{},{},{},{},{},{},{},{},{},{},{},{},{},{},{},{},{},{},{},{},{},{},{},{},{},{},{},{},{},{},{},{},{},{},{},{},{},{},{},{},{},{},{},{},{},{},{},{},{},{},{},{},{},{},{},{},{},{},{},{},{},{},{},{},{},{},{},{},{},{},{},{},{},{},{},{},{},{},{},{},{},{},{},{},{},{},{},{},{},{},{},{},{},{},{},{},{},{},{},{},{},{},{},{},{},{},{},{},{},{},{}]}]